<?xml version="1.0"?>
<disc>
<id>70046709</id>
<length>1129</length>
<title>al Score)</title>
<genre>cddb/soundtrack</genre>
<track index="1" offset="150">Arabian Nights, Reprise #1</track>
<track index="2" offset="2712">Babkak, Omar, Alladin, Kassim</track>
<track index="3" offset="15330">Arabian Nights, Reprise #2</track>
<track index="4" offset="17925">Friend Like Me</track>
<track index="5" offset="29762">Proud Of Your Boy</track>
<track index="6" offset="40982">How Quick they Forget</track>
<track index="7" offset="58985">Arabian Nights, Reprise #3</track>
<track index="8" offset="61780">High Adventure</track>
<track index="9" offset="81427">Arabian Nights, Reprise #4</track>
</disc>
